hello_there/__init__.py
hello_there/obiwan.py
hello_there_iv-0.0.1.dist-info/LICENSE
hello_there_iv-0.0.1.dist-info/METADATA
hello_there_iv-0.0.1.dist-info/WHEEL
hello_there_iv-0.0.1.dist-info/top_level.txt
hello_there_iv-0.0.1.dist-info/RECORD
